[
    {
        "date": [
            "1911",
            "1",
            "1"
        ],
        "temp": [
            14.8,
            20.4
        ],
        "rain": 0,
        "sun": 9
    },
    {
        "date": [
            "1911",
            "1",
            "2"
        ],
        "temp": [
            12.4,
            17.8
        ],
        "rain": 0,
        "sun": 9.1
    },
    {
        "date": [
            "1911",
            "1",
            "3"
        ],
        "temp": [
            12.7,
            18.3
        ],
        "rain": 0,
        "sun": 9.6
    },
    {
        "date": [
            "1911",
            "1",
            "4"
        ],
        "temp": [
            14.4,
            20.1
        ],
        "rain": 0,
        "sun": 9.2
    },
    {
        "date": [
            "1911",
            "1",
            "5"
        ],
        "temp": [
            14.7,
            23.6
        ],
        "rain": 0,
        "sun": 9
    },
    {
        "date": [
            "1911",
            "1",
            "6"
        ],
        "temp": [
            14.9,
            16.9
        ],
        "rain": 0,
        "sun": 0.1
    },
    {
        "date": [
            "1911",
            "1",
            "7"
        ],
        "temp": [
            14.2,
            17.3
        ],
        "rain": 0,
        "sun": 7.1
    },
    {
        "date": [
            "1911",
            "1",
            "8"
        ],
        "temp": [
            15.1,
            19.3
        ],
        "rain": 0,
        "sun": 7.7
    },
    {
        "date": [
            "1911",
            "1",
            "9"
        ],
        "temp": [
            15.7,
            19.7
        ],
        "rain": 0,
        "sun": 8.9
    },
    {
        "date": [
            "1911",
            "1",
            "10"
        ],
        "temp": [
            15.8,
            19.2
        ],
        "rain": 0,
        "sun": 9.5
    },
    {
        "date": [
            "1911",
            "1",
            "11"
        ],
        "temp": [
            11.3,
            20.8
        ],
        "rain": 0.6,
        "sun": 2
    },
    {
        "date": [
            "1911",
            "1",
            "12"
        ],
        "temp": [
            10.5,
            13.2
        ],
        "rain": 0,
        "sun": 0
    },
    {
        "date": [
            "1911",
            "1",
            "13"
        ],
        "temp": [
            11.8,
            14.8
        ],
        "rain": 0,
        "sun": 3.9
    },
    {
        "date": [
            "1911",
            "1",
            "14"
        ],
        "temp": [
            11.4,
            17.1
        ],
        "rain": 0,
        "sun": 5.7
    },
    {
        "date": [
            "1911",
            "1",
            "15"
        ],
        "temp": [
            9.2,
            13
        ],
        "rain": 0,
        "sun": 0
    },
    {
        "date": [
            "1911",
            "1",
            "16"
        ],
        "temp": [
            10.7,
            13.8
        ],
        "rain": 0,
        "sun": 0.4
    },
    {
        "date": [
            "1911",
            "1",
            "17"
        ],
        "temp": [
            9.9,
            14.3
        ],
        "rain": 0.8,
        "sun": 0
    },
    {
        "date": [
            "1911",
            "1",
            "18"
        ],
        "temp": [
            11,
            15.5
        ],
        "rain": 0,
        "sun": 0.9
    },
    {
        "date": [
            "1911",
            "1",
            "19"
        ],
        "temp": [
            8.6,
            11.9
        ],
        "rain": 0.1,
        "sun": 0
    },
    {
        "date": [
            "1911",
            "1",
            "20"
        ],
        "temp": [
            9.3,
            12.7
        ],
        "rain": 0,
        "sun": 0
    },
    {
        "date": [
            "1911",
            "1",
            "21"
        ],
        "temp": [
            11.1,
            15.3
        ],
        "rain": 0.4,
        "sun": 0.1
    },
    {
        "date": [
            "1911",
            "1",
            "22"
        ],
        "temp": [
            12.4,
            15.4
        ],
        "rain": 0,
        "sun": 0.3
    },
    {
        "date": [
            "1911",
            "1",
            "23"
        ],
        "temp": [
            11.4,
            17.1
        ],
        "rain": 0,
        "sun": 9.2
    },
    {
        "date": [
            "1911",
            "1",
            "24"
        ],
        "temp": [
            11.7,
            16.7
        ],
        "rain": 0,
        "sun": 9.7
    },
    {
        "date": [
            "1911",
            "1",
            "25"
        ],
        "temp": [
            13.3,
            17.5
        ],
        "rain": 0,
        "sun": 10
    },
    {
        "date": [
            "1911",
            "1",
            "26"
        ],
        "temp": [
            14.9,
            17.6
        ],
        "rain": 0,
        "sun": 6.6
    },
    {
        "date": [
            "1911",
            "1",
            "27"
        ],
        "temp": [
            15.9,
            19.4
        ],
        "rain": 0,
        "sun": 8
    },
    {
        "date": [
            "1911",
            "1",
            "28"
        ],
        "temp": [
            16.6,
            18.6
        ],
        "rain": 0,
        "sun": 0.3
    },
    {
        "date": [
            "1911",
            "1",
            "29"
        ],
        "temp": [
            15.3,
            17.1
        ],
        "rain": 0.2,
        "sun": 0.5
    },
    {
        "date": [
            "1911",
            "1",
            "30"
        ],
        "temp": [
            16.1,
            21
        ],
        "rain": 15.8,
        "sun": 0.2
    },
    {
        "date": [
            "1911",
            "1",
            "31"
        ],
        "temp": [
            17.8,
            20.1
        ],
        "rain": 0.8,
        "sun": 2.2
    },
    {
        "date": [
            "1911",
            "2",
            "1"
        ],
        "temp": [
            17.7,
            22.7
        ],
        "rain": 0,
        "sun": 5.5
    },
    {
        "date": [
            "1911",
            "2",
            "2"
        ],
        "temp": [
            15.1,
            20.3
        ],
        "rain": 0,
        "sun": 4.3
    },
    {
        "date": [
            "1911",
            "2",
            "3"
        ],
        "temp": [
            10.8,
            16.5
        ],
        "rain": 0,
        "sun": 6.3
    },
    {
        "date": [
            "1911",
            "2",
            "4"
        ],
        "temp": [
            9.9,
            16.2
        ],
        "rain": 0,
        "sun": 9.8
    },
    {
        "date": [
            "1911",
            "2",
            "5"
        ],
        "temp": [
            12.3,
            17.7
        ],
        "rain": 0,
        "sun": 10.1
    },
    {
        "date": [
            "1911",
            "2",
            "6"
        ],
        "temp": [
            13.2,
            16.7
        ],
        "rain": 0,
        "sun": 8.6
    },
    {
        "date": [
            "1911",
            "2",
            "7"
        ],
        "temp": [
            13.9,
            17.2
        ],
        "rain": 0,
        "sun": 5.5
    },
    {
        "date": [
            "1911",
            "2",
            "8"
        ],
        "temp": [
            14.8,
            19.1
        ],
        "rain": 0,
        "sun": 6.9
    },
    {
        "date": [
            "1911",
            "2",
            "9"
        ],
        "temp": [
            15.3,
            18.3
        ],
        "rain": 0,
        "sun": 9.7
    },
    {
        "date": [
            "1911",
            "2",
            "10"
        ],
        "temp": [
            14.6,
            18.9
        ],
        "rain": 0,
        "sun": 9.9
    },
    {
        "date": [
            "1911",
            "2",
            "11"
        ],
        "temp": [
            15.4,
            20.6
        ],
        "rain": 0,
        "sun": 10
    },
    {
        "date": [
            "1911",
            "2",
            "12"
        ],
        "temp": [
            15.5,
            19.8
        ],
        "rain": 0,
        "sun": 6.8
    },
    {
        "date": [
            "1911",
            "2",
            "13"
        ],
        "temp": [
            15.7,
            18.2
        ],
        "rain": 0,
        "sun": 0.3
    },
    {
        "date": [
            "1911",
            "2",
            "14"
        ],
        "temp": [
            16.4,
            22.5
        ],
        "rain": 0,
        "sun": 6.9
    },
    {
        "date": [
            "1911",
            "2",
            "15"
        ],
        "temp": [
            16.1,
            23.4
        ],
        "rain": 0,
        "sun": 10.4
    },
    {
        "date": [
            "1911",
            "2",
            "16"
        ],
        "temp": [
            14.8,
            18
        ],
        "rain": 0,
        "sun": 3.4
    },
    {
        "date": [
            "1911",
            "2",
            "17"
        ],
        "temp": [
            13.8,
            18.2
        ],
        "rain": 0,
        "sun": 5.3
    },
    {
        "date": [
            "1911",
            "2",
            "18"
        ],
        "temp": [
            13.8,
            17.5
        ],
        "rain": 0,
        "sun": 4.5
    },
    {
        "date": [
            "1911",
            "2",
            "19"
        ],
        "temp": [
            13.5,
            17
        ],
        "rain": 0,
        "sun": 3.7
    },
    {
        "date": [
            "1911",
            "2",
            "20"
        ],
        "temp": [
            12.5,
            17.2
        ],
        "rain": 0,
        "sun": 10.3
    },
    {
        "date": [
            "1911",
            "2",
            "21"
        ],
        "temp": [
            13.6,
            18.8
        ],
        "rain": 0,
        "sun": 4.3
    },
    {
        "date": [
            "1911",
            "2",
            "22"
        ],
        "temp": [
            13.8,
            19.3
        ],
        "rain": 0,
        "sun": 3
    },
    {
        "date": [
            "1911",
            "2",
            "23"
        ],
        "temp": [
            11,
            18.9
        ],
        "rain": 0,
        "sun": 10.3
    },
    {
        "date": [
            "1911",
            "2",
            "24"
        ],
        "temp": [
            8.4,
            16.7
        ],
        "rain": 0,
        "sun": 7
    },
    {
        "date": [
            "1911",
            "2",
            "25"
        ],
        "temp": [
            10.8,
            15.6
        ],
        "rain": 0,
        "sun": 0
    },
    {
        "date": [
            "1911",
            "2",
            "26"
        ],
        "temp": [
            9.1,
            16.2
        ],
        "rain": 0,
        "sun": 10.5
    },
    {
        "date": [
            "1911",
            "2",
            "27"
        ],
        "temp": [
            11.5,
            18.6
        ],
        "rain": 0,
        "sun": 6
    },
    {
        "date": [
            "1911",
            "2",
            "28"
        ],
        "temp": [
            13.7,
            20.4
        ],
        "rain": 0,
        "sun": 10.6
    },
    {
        "date": [
            "1911",
            "3",
            "1"
        ],
        "temp": [
            14.6,
            23.8
        ],
        "rain": 0,
        "sun": 9.8
    },
    {
        "date": [
            "1911",
            "3",
            "2"
        ],
        "temp": [
            14.5,
            20.3
        ],
        "rain": 0,
        "sun": 10
    },
    {
        "date": [
            "1911",
            "3",
            "3"
        ],
        "temp": [
            14.5,
            18.7
        ],
        "rain": 0,
        "sun": 8.1
    },
    {
        "date": [
            "1911",
            "3",
            "4"
        ],
        "temp": [
            16.4,
            19.4
        ],
        "rain": 0,
        "sun": 4.7
    },
    {
        "date": [
            "1911",
            "3",
            "5"
        ],
        "temp": [
            17.9,
            24.7
        ],
        "rain": 0,
        "sun": 3.1
    },
    {
        "date": [
            "1911",
            "3",
            "6"
        ],
        "temp": [
            19.2,
            25.8
        ],
        "rain": 0,
        "sun": 6.7
    },
    {
        "date": [
            "1911",
            "3",
            "7"
        ],
        "temp": [
            15.8,
            19.6
        ],
        "rain": 2.8,
        "sun": 0
    },
    {
        "date": [
            "1911",
            "3",
            "8"
        ],
        "temp": [
            16.5,
            19.6
        ],
        "rain": 0,
        "sun": 2.4
    },
    {
        "date": [
            "1911",
            "3",
            "9"
        ],
        "temp": [
            17.8,
            23.3
        ],
        "rain": 0,
        "sun": 5.8
    },
    {
        "date": [
            "1911",
            "3",
            "10"
        ],
        "temp": [
            19.4,
            22.3
        ],
        "rain": 26.4,
        "sun": 0
    },
    {
        "date": [
            "1911",
            "3",
            "11"
        ],
        "temp": [
            15.5,
            20
        ],
        "rain": 3.2,
        "sun": 1.9
    },
    {
        "date": [
            "1911",
            "3",
            "12"
        ],
        "temp": [
            15.5,
            19.5
        ],
        "rain": 0.3,
        "sun": 1.2
    },
    {
        "date": [
            "1911",
            "3",
            "13"
        ],
        "temp": [
            18.9,
            21.1
        ],
        "rain": 0,
        "sun": 0
    },
    {
        "date": [
            "1911",
            "3",
            "14"
        ],
        "temp": [
            19.4,
            24.7
        ],
        "rain": 0.1,
        "sun": 1.8
    },
    {
        "date": [
            "1911",
            "3",
            "15"
        ],
        "temp": [
            22.5,
            25.9
        ],
        "rain": 0,
        "sun": 6.6
    },
    {
        "date": [
            "1911",
            "3",
            "16"
        ],
        "temp": [
            22.2,
            26.2
        ],
        "rain": 0,
        "sun": 4.3
    },
    {
        "date": [
            "1911",
            "3",
            "17"
        ],
        "temp": [
            13.8,
            23.1
        ],
        "rain": 15.5,
        "sun": 0
    },
    {
        "date": [
            "1911",
            "3",
            "18"
        ],
        "temp": [
            12.3,
            19.4
        ],
        "rain": 0,
        "sun": 10.1
    },
    {
        "date": [
            "1911",
            "3",
            "19"
        ],
        "temp": [
            14.8,
            16.3
        ],
        "rain": 0.4,
        "sun": 0.1
    },
    {
        "date": [
            "1911",
            "3",
            "20"
        ],
        "temp": [
            13.4,
            16.1
        ],
        "rain": 11.3,
        "sun": 0
    },
    {
        "date": [
            "1911",
            "3",
            "21"
        ],
        "temp": [
            15.6,
            19.3
        ],
        "rain": 15.3,
        "sun": 0
    },
    {
        "date": [
            "1911",
            "3",
            "22"
        ],
        "temp": [
            17.1,
            19.2
        ],
        "rain": 13.7,
        "sun": 0
    },
    {
        "date": [
            "1911",
            "3",
            "23"
        ],
        "temp": [
            15.4,
            18.1
        ],
        "rain": 0.4,
        "sun": 0
    },
    {
        "date": [
            "1911",
            "3",
            "24"
        ],
        "temp": [
            14.2,
            16.6
        ],
        "rain": 0,
        "sun": 0
    },
    {
        "date": [
            "1911",
            "3",
            "25"
        ],
        "temp": [
            14.2,
            17
        ],
        "rain": 7.1,
        "sun": 0
    },
    {
        "date": [
            "1911",
            "3",
            "26"
        ],
        "temp": [
            15.1,
            17
        ],
        "rain": 0,
        "sun": 2.4
    },
    {
        "date": [
            "1911",
            "3",
            "27"
        ],
        "temp": [
            15.6,
            19.9
        ],
        "rain": 0,
        "sun": 8.7
    },
    {
        "date": [
            "1911",
            "3",
            "28"
        ],
        "temp": [
            16.5,
            20.5
        ],
        "rain": 0,
        "sun": 9.8
    },
    {
        "date": [
            "1911",
            "3",
            "29"
        ],
        "temp": [
            17.7,
            21.3
        ],
        "rain": 0,
        "sun": 4.2
    },
    {
        "date": [
            "1911",
            "3",
            "30"
        ],
        "temp": [
            19.1,
            24
        ],
        "rain": 0,
        "sun": 4.5
    },
    {
        "date": [
            "1911",
            "3",
            "31"
        ],
        "temp": [
            17.2,
            23.2
        ],
        "rain": 0.9,
        "sun": 0.2
    },
    {
        "date": [
            "1911",
            "4",
            "1"
        ],
        "temp": [
            16.3,
            18.7
        ],
        "rain": 0.8,
        "sun": 0.9
    },
    {
        "date": [
            "1911",
            "4",
            "2"
        ],
        "temp": [
            16.7,
            20.3
        ],
        "rain": 0,
        "sun": 9.4
    },
    {
        "date": [
            "1911",
            "4",
            "3"
        ],
        "temp": [
            16.9,
            20.7
        ],
        "rain": 0,
        "sun": 6.3
    },
    {
        "date": [
            "1911",
            "4",
            "4"
        ],
        "temp": [
            17.6,
            22.6
        ],
        "rain": 0,
        "sun": 3.6
    },
    {
        "date": [
            "1911",
            "4",
            "5"
        ],
        "temp": [
            19.5,
            24.4
        ],
        "rain": 0,
        "sun": 9.7
    },
    {
        "date": [
            "1911",
            "4",
            "6"
        ],
        "temp": [
            18.9,
            21.2
        ],
        "rain": 0.5,
        "sun": 3.3
    },
    {
        "date": [
            "1911",
            "4",
            "7"
        ],
        "temp": [
            18.9,
            22.2
        ],
        "rain": 0,
        "sun": 1.9
    },
    {
        "date": [
            "1911",
            "4",
            "8"
        ],
        "temp": [
            19.8,
            24.7
        ],
        "rain": 0,
        "sun": 8.8
    },
    {
        "date": [
            "1911",
            "4",
            "9"
        ],
        "temp": [
            21.1,
            25.3
        ],
        "rain": 0.1,
        "sun": 3.8
    },
    {
        "date": [
            "1911",
            "4",
            "10"
        ],
        "temp": [
            20.4,
            23.1
        ],
        "rain": 30.9,
        "sun": 1.3
    },
    {
        "date": [
            "1911",
            "4",
            "11"
        ],
        "temp": [
            19,
            24.5
        ],
        "rain": 0,
        "sun": 8.4
    },
    {
        "date": [
            "1911",
            "4",
            "12"
        ],
        "temp": [
            17.6,
            23.8
        ],
        "rain": 54.9,
        "sun": 4.1
    },
    {
        "date": [
            "1911",
            "4",
            "13"
        ],
        "temp": [
            17.3,
            21.5
        ],
        "rain": 5.3,
        "sun": 1.8
    },
    {
        "date": [
            "1911",
            "4",
            "14"
        ],
        "temp": [
            18.5,
            21.2
        ],
        "rain": 7.1,
        "sun": 0.3
    },
    {
        "date": [
            "1911",
            "4",
            "15"
        ],
        "temp": [
            19,
            22.3
        ],
        "rain": 0,
        "sun": 6.6
    },
    {
        "date": [
            "1911",
            "4",
            "16"
        ],
        "temp": [
            18.4,
            21.1
        ],
        "rain": 0,
        "sun": 0.9
    },
    {
        "date": [
            "1911",
            "4",
            "17"
        ],
        "temp": [
            16.7,
            20
        ],
        "rain": 2.3,
        "sun": 0
    },
    {
        "date": [
            "1911",
            "4",
            "18"
        ],
        "temp": [
            17.3,
            21.3
        ],
        "rain": 0,
        "sun": 1.8
    },
    {
        "date": [
            "1911",
            "4",
            "19"
        ],
        "temp": [
            17.2,
            20.6
        ],
        "rain": 0.4,
        "sun": 0.1
    },
    {
        "date": [
            "1911",
            "4",
            "20"
        ],
        "temp": [
            18.3,
            25.1
        ],
        "rain": 0,
        "sun": 6.1
    },
    {
        "date": [
            "1911",
            "4",
            "21"
        ],
        "temp": [
            19.8,
            24.3
        ],
        "rain": 0,
        "sun": 9.8
    },
    {
        "date": [
            "1911",
            "4",
            "22"
        ],
        "temp": [
            19.7,
            26.7
        ],
        "rain": 0,
        "sun": 11.3
    },
    {
        "date": [
            "1911",
            "4",
            "23"
        ],
        "temp": [
            21.2,
            26.1
        ],
        "rain": 0.7,
        "sun": 6.3
    },
    {
        "date": [
            "1911",
            "4",
            "24"
        ],
        "temp": [
            22.6,
            28.1
        ],
        "rain": 0,
        "sun": 9.7
    },
    {
        "date": [
            "1911",
            "4",
            "25"
        ],
        "temp": [
            22.1,
            29.8
        ],
        "rain": 0,
        "sun": 11
    },
    {
        "date": [
            "1911",
            "4",
            "26"
        ],
        "temp": [
            21.4,
            30.5
        ],
        "rain": 0,
        "sun": 9.3
    },
    {
        "date": [
            "1911",
            "4",
            "27"
        ],
        "temp": [
            18.4,
            20.6
        ],
        "rain": 9.4,
        "sun": 0.1
    },
    {
        "date": [
            "1911",
            "4",
            "28"
        ],
        "temp": [
            20,
            22.2
        ],
        "rain": 1.1,
        "sun": 0
    },
    {
        "date": [
            "1911",
            "4",
            "29"
        ],
        "temp": [
            21.1,
            23.4
        ],
        "rain": 5.6,
        "sun": 2.1
    },
    {
        "date": [
            "1911",
            "4",
            "30"
        ],
        "temp": [
            21.9,
            23.9
        ],
        "rain": 31.4,
        "sun": 0.1
    },
    {
        "date": [
            "1911",
            "5",
            "1"
        ],
        "temp": [
            22.5,
            27.2
        ],
        "rain": 56.3,
        "sun": 1.5
    },
    {
        "date": [
            "1911",
            "5",
            "2"
        ],
        "temp": [
            21.1,
            22.6
        ],
        "rain": 23.1,
        "sun": 0
    },
    {
        "date": [
            "1911",
            "5",
            "3"
        ],
        "temp": [
            21.3,
            23.6
        ],
        "rain": 2.1,
        "sun": 0.3
    },
    {
        "date": [
            "1911",
            "5",
            "4"
        ],
        "temp": [
            22.6,
            27.1
        ],
        "rain": 0,
        "sun": 10.7
    },
    {
        "date": [
            "1911",
            "5",
            "5"
        ],
        "temp": [
            22.9,
            27.3
        ],
        "rain": 0,
        "sun": 9
    },
    {
        "date": [
            "1911",
            "5",
            "6"
        ],
        "temp": [
            23.7,
            25.9
        ],
        "rain": 0,
        "sun": 6.2
    },
    {
        "date": [
            "1911",
            "5",
            "7"
        ],
        "temp": [
            22.4,
            24.3
        ],
        "rain": 1.7,
        "sun": 0.2
    },
    {
        "date": [
            "1911",
            "5",
            "8"
        ],
        "temp": [
            21.9,
            23.6
        ],
        "rain": 25.6,
        "sun": 0
    },
    {
        "date": [
            "1911",
            "5",
            "9"
        ],
        "temp": [
            22.1,
            24.1
        ],
        "rain": 1.7,
        "sun": 0.5
    },
    {
        "date": [
            "1911",
            "5",
            "10"
        ],
        "temp": [
            22.4,
            23.9
        ],
        "rain": 32.7,
        "sun": 0
    },
    {
        "date": [
            "1911",
            "5",
            "11"
        ],
        "temp": [
            22.8,
            25.3
        ],
        "rain": 51,
        "sun": 1.1
    },
    {
        "date": [
            "1911",
            "5",
            "12"
        ],
        "temp": [
            22.9,
            24.7
        ],
        "rain": 28.2,
        "sun": 0
    },
    {
        "date": [
            "1911",
            "5",
            "13"
        ],
        "temp": [
            22.9,
            28.7
        ],
        "rain": 0.6,
        "sun": 8.5
    },
    {
        "date": [
            "1911",
            "5",
            "14"
        ],
        "temp": [
            24.8,
            28.6
        ],
        "rain": 5.4,
        "sun": 2.2
    },
    {
        "date": [
            "1911",
            "5",
            "15"
        ],
        "temp": [
            21.6,
            24.8
        ],
        "rain": 20.2,
        "sun": 0
    },
    {
        "date": [
            "1911",
            "5",
            "16"
        ],
        "temp": [
            20.1,
            22
        ],
        "rain": 29.3,
        "sun": 0
    },
    {
        "date": [
            "1911",
            "5",
            "17"
        ],
        "temp": [
            20.4,
            24.5
        ],
        "rain": 0.4,
        "sun": 2.6
    },
    {
        "date": [
            "1911",
            "5",
            "18"
        ],
        "temp": [
            22,
            24.2
        ],
        "rain": 0.2,
        "sun": 2.1
    },
    {
        "date": [
            "1911",
            "5",
            "19"
        ],
        "temp": [
            22.6,
            24.1
        ],
        "rain": 1.9,
        "sun": 0
    },
    {
        "date": [
            "1911",
            "5",
            "20"
        ],
        "temp": [
            22.8,
            25.1
        ],
        "rain": 69.7,
        "sun": 0
    },
    {
        "date": [
            "1911",
            "5",
            "21"
        ],
        "temp": [
            21.7,
            30.1
        ],
        "rain": 0.4,
        "sun": 7.4
    },
    {
        "date": [
            "1911",
            "5",
            "22"
        ],
        "temp": [
            23.4,
            26.6
        ],
        "rain": 30.3,
        "sun": 0.5
    },
    {
        "date": [
            "1911",
            "5",
            "23"
        ],
        "temp": [
            23.2,
            26.1
        ],
        "rain": 0,
        "sun": 4.5
    },
    {
        "date": [
            "1911",
            "5",
            "24"
        ],
        "temp": [
            23.3,
            24.8
        ],
        "rain": 33.8,
        "sun": 0
    },
    {
        "date": [
            "1911",
            "5",
            "25"
        ],
        "temp": [
            23.7,
            27.8
        ],
        "rain": 12.7,
        "sun": 4.8
    },
    {
        "date": [
            "1911",
            "5",
            "26"
        ],
        "temp": [
            23.6,
            27.9
        ],
        "rain": 37.6,
        "sun": 0.7
    },
    {
        "date": [
            "1911",
            "5",
            "27"
        ],
        "temp": [
            23.2,
            26.6
        ],
        "rain": 62.2,
        "sun": 0
    },
    {
        "date": [
            "1911",
            "5",
            "28"
        ],
        "temp": [
            23.9,
            28.6
        ],
        "rain": 0,
        "sun": 1.8
    },
    {
        "date": [
            "1911",
            "5",
            "29"
        ],
        "temp": [
            25,
            30.1
        ],
        "rain": 5.2,
        "sun": 9.7
    },
    {
        "date": [
            "1911",
            "5",
            "30"
        ],
        "temp": [
            24.4,
            30.5
        ],
        "rain": 1.4,
        "sun": 11.4
    },
    {
        "date": [
            "1911",
            "5",
            "31"
        ],
        "temp": [
            22.1,
            25.6
        ],
        "rain": 29.9,
        "sun": 0.4
    },
    {
        "date": [
            "1911",
            "6",
            "1"
        ],
        "temp": [
            23.9,
            27.4
        ],
        "rain": 3.3,
        "sun": 3.2
    },
    {
        "date": [
            "1911",
            "6",
            "2"
        ],
        "temp": [
            24.3,
            30
        ],
        "rain": 0,
        "sun": 10
    },
    {
        "date": [
            "1911",
            "6",
            "3"
        ],
        "temp": [
            25.4,
            29.9
        ],
        "rain": 0.1,
        "sun": 8.2
    },
    {
        "date": [
            "1911",
            "6",
            "4"
        ],
        "temp": [
            26.1,
            30.6
        ],
        "rain": 2.9,
        "sun": 7.6
    },
    {
        "date": [
            "1911",
            "6",
            "5"
        ],
        "temp": [
            26,
            29.6
        ],
        "rain": 0.9,
        "sun": 9.6
    },
    {
        "date": [
            "1911",
            "6",
            "6"
        ],
        "temp": [
            26.7,
            29.7
        ],
        "rain": 5.5,
        "sun": 10.6
    },
    {
        "date": [
            "1911",
            "6",
            "7"
        ],
        "temp": [
            26.9,
            30
        ],
        "rain": 0.8,
        "sun": 10.4
    },
    {
        "date": [
            "1911",
            "6",
            "8"
        ],
        "temp": [
            26.8,
            31
        ],
        "rain": 0.7,
        "sun": 11.1
    },
    {
        "date": [
            "1911",
            "6",
            "9"
        ],
        "temp": [
            26.4,
            29.9
        ],
        "rain": 4.5,
        "sun": 4.6
    },
    {
        "date": [
            "1911",
            "6",
            "10"
        ],
        "temp": [
            26,
            30.9
        ],
        "rain": 0,
        "sun": 11.7
    },
    {
        "date": [
            "1911",
            "6",
            "11"
        ],
        "temp": [
            25.9,
            31.3
        ],
        "rain": 0,
        "sun": 10.1
    },
    {
        "date": [
            "1911",
            "6",
            "12"
        ],
        "temp": [
            26.6,
            30.1
        ],
        "rain": 0,
        "sun": 10.8
    },
    {
        "date": [
            "1911",
            "6",
            "13"
        ],
        "temp": [
            26.2,
            31.9
        ],
        "rain": 0,
        "sun": 11.1
    },
    {
        "date": [
            "1911",
            "6",
            "14"
        ],
        "temp": [
            26.8,
            31.4
        ],
        "rain": 17.2,
        "sun": 8.8
    },
    {
        "date": [
            "1911",
            "6",
            "15"
        ],
        "temp": [
            27.2,
            31.9
        ],
        "rain": 0.1,
        "sun": 10.9
    },
    {
        "date": [
            "1911",
            "6",
            "16"
        ],
        "temp": [
            26.8,
            31.9
        ],
        "rain": 1.8,
        "sun": 9.9
    },
    {
        "date": [
            "1911",
            "6",
            "17"
        ],
        "temp": [
            27.3,
            32.1
        ],
        "rain": 4.4,
        "sun": 10.4
    },
    {
        "date": [
            "1911",
            "6",
            "18"
        ],
        "temp": [
            27.7,
            32.9
        ],
        "rain": 4.2,
        "sun": 6.6
    },
    {
        "date": [
            "1911",
            "6",
            "19"
        ],
        "temp": [
            25.9,
            32.4
        ],
        "rain": 0.9,
        "sun": 8.5
    },
    {
        "date": [
            "1911",
            "6",
            "20"
        ],
        "temp": [
            26.5,
            29.9
        ],
        "rain": 28.4,
        "sun": 6.1
    },
    {
        "date": [
            "1911",
            "6",
            "21"
        ],
        "temp": [
            25.4,
            29.2
        ],
        "rain": 38.5,
        "sun": 1
    },
    {
        "date": [
            "1911",
            "6",
            "22"
        ],
        "temp": [
            26.1,
            30.7
        ],
        "rain": 6.6,
        "sun": 7.7
    },
    {
        "date": [
            "1911",
            "6",
            "23"
        ],
        "temp": [
            27.4,
            30.9
        ],
        "rain": 0,
        "sun": 8.4
    },
    {
        "date": [
            "1911",
            "6",
            "24"
        ],
        "temp": [
            27.1,
            31.1
        ],
        "rain": 0,
        "sun": 11.4
    },
    {
        "date": [
            "1911",
            "6",
            "25"
        ],
        "temp": [
            27.5,
            30.8
        ],
        "rain": 1.5,
        "sun": 8
    },
    {
        "date": [
            "1911",
            "6",
            "26"
        ],
        "temp": [
            28.1,
            30.8
        ],
        "rain": 0.2,
        "sun": 6.9
    },
    {
        "date": [
            "1911",
            "6",
            "27"
        ],
        "temp": [
            27.9,
            31
        ],
        "rain": 0.3,
        "sun": 7.6
    },
    {
        "date": [
            "1911",
            "6",
            "28"
        ],
        "temp": [
            27.5,
            30.1
        ],
        "rain": 6.1,
        "sun": 1.4
    },
    {
        "date": [
            "1911",
            "6",
            "29"
        ],
        "temp": [
            27,
            30.4
        ],
        "rain": 0,
        "sun": 7.7
    },
    {
        "date": [
            "1911",
            "6",
            "30"
        ],
        "temp": [
            26.3,
            30.6
        ],
        "rain": 0.1,
        "sun": 8.2
    },
    {
        "date": [
            "1911",
            "7",
            "1"
        ],
        "temp": [
            26.1,
            30.7
        ],
        "rain": 0,
        "sun": 9.9
    },
    {
        "date": [
            "1911",
            "7",
            "2"
        ],
        "temp": [
            25.6,
            29.2
        ],
        "rain": 0,
        "sun": 10.4
    },
    {
        "date": [
            "1911",
            "7",
            "3"
        ],
        "temp": [
            23.9,
            29.7
        ],
        "rain": 34.5,
        "sun": 0.7
    },
    {
        "date": [
            "1911",
            "7",
            "4"
        ],
        "temp": [
            24.4,
            26.7
        ],
        "rain": 40.5,
        "sun": 0
    },
    {
        "date": [
            "1911",
            "7",
            "5"
        ],
        "temp": [
            25.6,
            29.4
        ],
        "rain": 5.1,
        "sun": 8
    },
    {
        "date": [
            "1911",
            "7",
            "6"
        ],
        "temp": [
            25.7,
            29.4
        ],
        "rain": 5.1,
        "sun": 5.7
    },
    {
        "date": [
            "1911",
            "7",
            "7"
        ],
        "temp": [
            25.6,
            29
        ],
        "rain": 0.3,
        "sun": 8.5
    },
    {
        "date": [
            "1911",
            "7",
            "8"
        ],
        "temp": [
            25.5,
            30.3
        ],
        "rain": 0,
        "sun": 8.5
    },
    {
        "date": [
            "1911",
            "7",
            "9"
        ],
        "temp": [
            26.1,
            30.7
        ],
        "rain": 0,
        "sun": 10.9
    },
    {
        "date": [
            "1911",
            "7",
            "10"
        ],
        "temp": [
            26.1,
            31.3
        ],
        "rain": 0,
        "sun": 11.8
    },
    {
        "date": [
            "1911",
            "7",
            "11"
        ],
        "temp": [
            26.4,
            31.1
        ],
        "rain": 0,
        "sun": 8.4
    },
    {
        "date": [
            "1911",
            "7",
            "12"
        ],
        "temp": [
            26.4,
            30.8
        ],
        "rain": 1,
        "sun": 9.1
    },
    {
        "date": [
            "1911",
            "7",
            "13"
        ],
        "temp": [
            25.8,
            31.1
        ],
        "rain": 3.5,
        "sun": 9.5
    },
    {
        "date": [
            "1911",
            "7",
            "14"
        ],
        "temp": [
            26.1,
            30.5
        ],
        "rain": 0.9,
        "sun": 8.7
    },
    {
        "date": [
            "1911",
            "7",
            "15"
        ],
        "temp": [
            25.6,
            31.3
        ],
        "rain": 0,
        "sun": 8.1
    },
    {
        "date": [
            "1911",
            "7",
            "16"
        ],
        "temp": [
            27.5,
            32.9
        ],
        "rain": 0,
        "sun": 9.3
    },
    {
        "date": [
            "1911",
            "7",
            "17"
        ],
        "temp": [
            28,
            32.2
        ],
        "rain": 0,
        "sun": 10.9
    },
    {
        "date": [
            "1911",
            "7",
            "18"
        ],
        "temp": [
            27.8,
            31.6
        ],
        "rain": 0,
        "sun": 8.5
    },
    {
        "date": [
            "1911",
            "7",
            "19"
        ],
        "temp": [
            25,
            28.7
        ],
        "rain": 34.2,
        "sun": 1.1
    },
    {
        "date": [
            "1911",
            "7",
            "20"
        ],
        "temp": [
            25.1,
            28.6
        ],
        "rain": 12,
        "sun": 4
    },
    {
        "date": [
            "1911",
            "7",
            "21"
        ],
        "temp": [
            25.5,
            28.8
        ],
        "rain": 24.2,
        "sun": 4.3
    },
    {
        "date": [
            "1911",
            "7",
            "22"
        ],
        "temp": [
            25.5,
            29.5
        ],
        "rain": 4.3,
        "sun": 7.5
    },
    {
        "date": [
            "1911",
            "7",
            "23"
        ],
        "temp": [
            26.3,
            29.4
        ],
        "rain": 0,
        "sun": 12
    },
    {
        "date": [
            "1911",
            "7",
            "24"
        ],
        "temp": [
            25.4,
            31.4
        ],
        "rain": 0,
        "sun": 11.7
    },
    {
        "date": [
            "1911",
            "7",
            "25"
        ],
        "temp": [
            25.6,
            32
        ],
        "rain": 0,
        "sun": 11.6
    },
    {
        "date": [
            "1911",
            "7",
            "26"
        ],
        "temp": [
            26.2,
            32.4
        ],
        "rain": 1.8,
        "sun": 8
    },
    {
        "date": [
            "1911",
            "7",
            "27"
        ],
        "temp": [
            25.2,
            28.4
        ],
        "rain": 36.6,
        "sun": 0
    },
    {
        "date": [
            "1911",
            "7",
            "28"
        ],
        "temp": [
            26.4,
            30.2
        ],
        "rain": 1.1,
        "sun": 8.4
    },
    {
        "date": [
            "1911",
            "7",
            "29"
        ],
        "temp": [
            25.7,
            31.2
        ],
        "rain": 0,
        "sun": 11.3
    },
    {
        "date": [
            "1911",
            "7",
            "30"
        ],
        "temp": [
            26.2,
            31.6
        ],
        "rain": 0,
        "sun": 11.9
    },
    {
        "date": [
            "1911",
            "7",
            "31"
        ],
        "temp": [
            26.4,
            31.7
        ],
        "rain": 0,
        "sun": 11.2
    },
    {
        "date": [
            "1911",
            "8",
            "1"
        ],
        "temp": [
            26.4,
            32.9
        ],
        "rain": 0,
        "sun": 11.7
    },
    {
        "date": [
            "1911",
            "8",
            "2"
        ],
        "temp": [
            26.8,
            31.8
        ],
        "rain": 3.6,
        "sun": 7
    },
    {
        "date": [
            "1911",
            "8",
            "3"
        ],
        "temp": [
            25,
            28.8
        ],
        "rain": 4.7,
        "sun": 6.1
    },
    {
        "date": [
            "1911",
            "8",
            "4"
        ],
        "temp": [
            24.6,
            27.1
        ],
        "rain": 46,
        "sun": 0.7
    },
    {
        "date": [
            "1911",
            "8",
            "5"
        ],
        "temp": [
            24.4,
            27
        ],
        "rain": 218.6,
        "sun": 0
    },
    {
        "date": [
            "1911",
            "8",
            "6"
        ],
        "temp": [
            23.5,
            27.1
        ],
        "rain": 168.2,
        "sun": 0
    },
    {
        "date": [
            "1911",
            "8",
            "7"
        ],
        "temp": [
            26.3,
            29.4
        ],
        "rain": 0,
        "sun": 7.8
    },
    {
        "date": [
            "1911",
            "8",
            "8"
        ],
        "temp": [
            26.2,
            30.5
        ],
        "rain": 0,
        "sun": 6.5
    },
    {
        "date": [
            "1911",
            "8",
            "9"
        ],
        "temp": [
            26.6,
            31.4
        ],
        "rain": 0,
        "sun": 11.3
    },
    {
        "date": [
            "1911",
            "8",
            "10"
        ],
        "temp": [
            27,
            30.4
        ],
        "rain": 0,
        "sun": 0.9
    },
    {
        "date": [
            "1911",
            "8",
            "11"
        ],
        "temp": [
            26.1,
            30.7
        ],
        "rain": 0,
        "sun": 8
    },
    {
        "date": [
            "1911",
            "8",
            "12"
        ],
        "temp": [
            26.3,
            31.3
        ],
        "rain": 0.6,
        "sun": 7.9
    },
    {
        "date": [
            "1911",
            "8",
            "13"
        ],
        "temp": [
            26.4,
            30.7
        ],
        "rain": 3.3,
        "sun": 4.4
    },
    {
        "date": [
            "1911",
            "8",
            "14"
        ],
        "temp": [
            24.2,
            29.4
        ],
        "rain": 23.2,
        "sun": 1
    },
    {
        "date": [
            "1911",
            "8",
            "15"
        ],
        "temp": [
            24.8,
            29.8
        ],
        "rain": 5.9,
        "sun": 2.3
    },
    {
        "date": [
            "1911",
            "8",
            "16"
        ],
        "temp": [
            25,
            28.2
        ],
        "rain": 65.1,
        "sun": 0
    },
    {
        "date": [
            "1911",
            "8",
            "17"
        ],
        "temp": [
            24.2,
            27.6
        ],
        "rain": 75.1,
        "sun": 0
    },
    {
        "date": [
            "1911",
            "8",
            "18"
        ],
        "temp": [
            24.4,
            27.2
        ],
        "rain": 75.6,
        "sun": 0
    },
    {
        "date": [
            "1911",
            "8",
            "19"
        ],
        "temp": [
            24.8,
            27.1
        ],
        "rain": 41.3,
        "sun": 0.2
    },
    {
        "date": [
            "1911",
            "8",
            "20"
        ],
        "temp": [
            24.6,
            28.2
        ],
        "rain": 30.3,
        "sun": 1.1
    },
    {
        "date": [
            "1911",
            "8",
            "21"
        ],
        "temp": [
            25.7,
            31.1
        ],
        "rain": 0,
        "sun": 9.2
    },
    {
        "date": [
            "1911",
            "8",
            "22"
        ],
        "temp": [
            25.9,
            29.7
        ],
        "rain": 0.3,
        "sun": 7.7
    },
    {
        "date": [
            "1911",
            "8",
            "23"
        ],
        "temp": [
            26.3,
            29.9
        ],
        "rain": 0.1,
        "sun": 10.6
    },
    {
        "date": [
            "1911",
            "8",
            "24"
        ],
        "temp": [
            25.8,
            30.6
        ],
        "rain": 0,
        "sun": 11
    },
    {
        "date": [
            "1911",
            "8",
            "25"
        ],
        "temp": [
            26.2,
            31.9
        ],
        "rain": 0,
        "sun": 10.7
    },
    {
        "date": [
            "1911",
            "8",
            "26"
        ],
        "temp": [
            26.8,
            33.9
        ],
        "rain": 0,
        "sun": 11.4
    },
    {
        "date": [
            "1911",
            "8",
            "27"
        ],
        "temp": [
            27.3,
            31.9
        ],
        "rain": 0,
        "sun": 10
    },
    {
        "date": [
            "1911",
            "8",
            "28"
        ],
        "temp": [
            27.6,
            32.4
        ],
        "rain": 0,
        "sun": 11.5
    },
    {
        "date": [
            "1911",
            "8",
            "29"
        ],
        "temp": [
            27.1,
            31.4
        ],
        "rain": 0,
        "sun": 11.6
    },
    {
        "date": [
            "1911",
            "8",
            "30"
        ],
        "temp": [
            26.9,
            32.5
        ],
        "rain": 1.5,
        "sun": 10.5
    },
    {
        "date": [
            "1911",
            "8",
            "31"
        ],
        "temp": [
            26.7,
            32
        ],
        "rain": 0,
        "sun": 9.4
    },
    {
        "date": [
            "1911",
            "9",
            "1"
        ],
        "temp": [
            27.4,
            31.8
        ],
        "rain": 0,
        "sun": 8.9
    },
    {
        "date": [
            "1911",
            "9",
            "2"
        ],
        "temp": [
            28.3,
            31.7
        ],
        "rain": 0,
        "sun": 0.5
    },
    {
        "date": [
            "1911",
            "9",
            "3"
        ],
        "temp": [
            23.9,
            29.2
        ],
        "rain": 67.2,
        "sun": 0
    },
    {
        "date": [
            "1911",
            "9",
            "4"
        ],
        "temp": [
            24.8,
            30.7
        ],
        "rain": 34.8,
        "sun": 3.1
    },
    {
        "date": [
            "1911",
            "9",
            "5"
        ],
        "temp": [
            25.3,
            30.3
        ],
        "rain": 1.6,
        "sun": 9.3
    },
    {
        "date": [
            "1911",
            "9",
            "6"
        ],
        "temp": [
            24.4,
            30.9
        ],
        "rain": 14.6,
        "sun": 6.7
    },
    {
        "date": [
            "1911",
            "9",
            "7"
        ],
        "temp": [
            24.5,
            28.6
        ],
        "rain": 0,
        "sun": 5.8
    },
    {
        "date": [
            "1911",
            "9",
            "8"
        ],
        "temp": [
            24.4,
            28.9
        ],
        "rain": 0,
        "sun": 4.4
    },
    {
        "date": [
            "1911",
            "9",
            "9"
        ],
        "temp": [
            24.2,
            27.2
        ],
        "rain": 0,
        "sun": 1.8
    },
    {
        "date": [
            "1911",
            "9",
            "10"
        ],
        "temp": [
            24.6,
            28.9
        ],
        "rain": 0,
        "sun": 10.6
    },
    {
        "date": [
            "1911",
            "9",
            "11"
        ],
        "temp": [
            24.8,
            29.9
        ],
        "rain": 1.8,
        "sun": 10.4
    },
    {
        "date": [
            "1911",
            "9",
            "12"
        ],
        "temp": [
            24.1,
            29.5
        ],
        "rain": 0,
        "sun": 10.4
    },
    {
        "date": [
            "1911",
            "9",
            "13"
        ],
        "temp": [
            24.2,
            28.8
        ],
        "rain": 0,
        "sun": 10.2
    },
    {
        "date": [
            "1911",
            "9",
            "14"
        ],
        "temp": [
            24.4,
            30.7
        ],
        "rain": 0,
        "sun": 9.9
    },
    {
        "date": [
            "1911",
            "9",
            "15"
        ],
        "temp": [
            24.9,
            30.6
        ],
        "rain": 0,
        "sun": 10.3
    },
    {
        "date": [
            "1911",
            "9",
            "16"
        ],
        "temp": [
            25.4,
            30.3
        ],
        "rain": 0,
        "sun": 9.6
    },
    {
        "date": [
            "1911",
            "9",
            "17"
        ],
        "temp": [
            26.1,
            33.4
        ],
        "rain": 0,
        "sun": 10
    },
    {
        "date": [
            "1911",
            "9",
            "18"
        ],
        "temp": [
            25.8,
            30
        ],
        "rain": 0.6,
        "sun": 3.5
    },
    {
        "date": [
            "1911",
            "9",
            "19"
        ],
        "temp": [
            24.4,
            28.1
        ],
        "rain": 24.9,
        "sun": 0.2
    },
    {
        "date": [
            "1911",
            "9",
            "20"
        ],
        "temp": [
            26,
            28.6
        ],
        "rain": 4.5,
        "sun": 6.2
    },
    {
        "date": [
            "1911",
            "9",
            "21"
        ],
        "temp": [
            25.4,
            30.1
        ],
        "rain": 0,
        "sun": 10.3
    },
    {
        "date": [
            "1911",
            "9",
            "22"
        ],
        "temp": [
            25,
            29.1
        ],
        "rain": 0,
        "sun": 10.8
    },
    {
        "date": [
            "1911",
            "9",
            "23"
        ],
        "temp": [
            25.8,
            28.1
        ],
        "rain": 0.1,
        "sun": 8.4
    },
    {
        "date": [
            "1911",
            "9",
            "24"
        ],
        "temp": [
            26,
            29.7
        ],
        "rain": 0,
        "sun": 8.6
    },
    {
        "date": [
            "1911",
            "9",
            "25"
        ],
        "temp": [
            25.8,
            29.1
        ],
        "rain": 0,
        "sun": 9.8
    },
    {
        "date": [
            "1911",
            "9",
            "26"
        ],
        "temp": [
            25.4,
            30.7
        ],
        "rain": 0,
        "sun": 10.1
    },
    {
        "date": [
            "1911",
            "9",
            "27"
        ],
        "temp": [
            25.4,
            31.2
        ],
        "rain": 0,
        "sun": 9.4
    },
    {
        "date": [
            "1911",
            "9",
            "28"
        ],
        "temp": [
            25.7,
            31.9
        ],
        "rain": 0,
        "sun": 1.9
    },
    {
        "date": [
            "1911",
            "9",
            "29"
        ],
        "temp": [
            26.5,
            33.3
        ],
        "rain": 1,
        "sun": 6.9
    },
    {
        "date": [
            "1911",
            "9",
            "30"
        ],
        "temp": [
            24.6,
            31.1
        ],
        "rain": 7.1,
        "sun": 3
    },
    {
        "date": [
            "1911",
            "10",
            "1"
        ],
        "temp": [
            24.9,
            29.7
        ],
        "rain": 5.5,
        "sun": 0.4
    },
    {
        "date": [
            "1911",
            "10",
            "2"
        ],
        "temp": [
            23.2,
            26.6
        ],
        "rain": 84.7,
        "sun": 0
    },
    {
        "date": [
            "1911",
            "10",
            "3"
        ],
        "temp": [
            25.3,
            29.2
        ],
        "rain": 0.6,
        "sun": 5.7
    },
    {
        "date": [
            "1911",
            "10",
            "4"
        ],
        "temp": [
            23.2,
            29.3
        ],
        "rain": 7.3,
        "sun": 6.5
    },
    {
        "date": [
            "1911",
            "10",
            "5"
        ],
        "temp": [
            23.1,
            27
        ],
        "rain": 3,
        "sun": 3.7
    },
    {
        "date": [
            "1911",
            "10",
            "6"
        ],
        "temp": [
            22.9,
            27.3
        ],
        "rain": 0,
        "sun": 10.5
    },
    {
        "date": [
            "1911",
            "10",
            "7"
        ],
        "temp": [
            22.9,
            27.1
        ],
        "rain": 0,
        "sun": 10.5
    },
    {
        "date": [
            "1911",
            "10",
            "8"
        ],
        "temp": [
            23.8,
            27.8
        ],
        "rain": 0,
        "sun": 10.3
    },
    {
        "date": [
            "1911",
            "10",
            "9"
        ],
        "temp": [
            23.6,
            27.2
        ],
        "rain": 5.9,
        "sun": 8.9
    },
    {
        "date": [
            "1911",
            "10",
            "10"
        ],
        "temp": [
            21.9,
            24.8
        ],
        "rain": 32.1,
        "sun": 2.1
    },
    {
        "date": [
            "1911",
            "10",
            "11"
        ],
        "temp": [
            22.5,
            26.3
        ],
        "rain": 0,
        "sun": 8.5
    },
    {
        "date": [
            "1911",
            "10",
            "12"
        ],
        "temp": [
            19.7,
            25.4
        ],
        "rain": 0,
        "sun": 3.3
    },
    {
        "date": [
            "1911",
            "10",
            "13"
        ],
        "temp": [
            17,
            20.2
        ],
        "rain": 1.1,
        "sun": 0
    },
    {
        "date": [
            "1911",
            "10",
            "14"
        ],
        "temp": [
            16.4,
            20.1
        ],
        "rain": 0.2,
        "sun": 0
    },
    {
        "date": [
            "1911",
            "10",
            "15"
        ],
        "temp": [
            18,
            25.1
        ],
        "rain": 0,
        "sun": 9.6
    },
    {
        "date": [
            "1911",
            "10",
            "16"
        ],
        "temp": [
            18.8,
            24.3
        ],
        "rain": 0,
        "sun": 10.6
    },
    {
        "date": [
            "1911",
            "10",
            "17"
        ],
        "temp": [
            19.1,
            24.4
        ],
        "rain": 0,
        "sun": 10.6
    },
    {
        "date": [
            "1911",
            "10",
            "18"
        ],
        "temp": [
            20.9,
            24.2
        ],
        "rain": 0,
        "sun": 9.6
    },
    {
        "date": [
            "1911",
            "10",
            "19"
        ],
        "temp": [
            20.5,
            24.7
        ],
        "rain": 0,
        "sun": 10.5
    },
    {
        "date": [
            "1911",
            "10",
            "20"
        ],
        "temp": [
            21.1,
            25
        ],
        "rain": 0,
        "sun": 10.2
    },
    {
        "date": [
            "1911",
            "10",
            "21"
        ],
        "temp": [
            21.3,
            25.1
        ],
        "rain": 0,
        "sun": 9.1
    },
    {
        "date": [
            "1911",
            "10",
            "22"
        ],
        "temp": [
            20.9,
            25.2
        ],
        "rain": 0,
        "sun": 9.6
    },
    {
        "date": [
            "1911",
            "10",
            "23"
        ],
        "temp": [
            20.5,
            25.9
        ],
        "rain": 0,
        "sun": 10.2
    },
    {
        "date": [
            "1911",
            "10",
            "24"
        ],
        "temp": [
            22.4,
            25.1
        ],
        "rain": 0,
        "sun": 7.2
    },
    {
        "date": [
            "1911",
            "10",
            "25"
        ],
        "temp": [
            22.3,
            25.3
        ],
        "rain": 3.1,
        "sun": 8.5
    },
    {
        "date": [
            "1911",
            "10",
            "26"
        ],
        "temp": [
            22.9,
            26.7
        ],
        "rain": 0,
        "sun": 5
    },
    {
        "date": [
            "1911",
            "10",
            "27"
        ],
        "temp": [
            22.4,
            24.5
        ],
        "rain": 1,
        "sun": 0.8
    },
    {
        "date": [
            "1911",
            "10",
            "28"
        ],
        "temp": [
            20.6,
            26.7
        ],
        "rain": 0,
        "sun": 10.6
    },
    {
        "date": [
            "1911",
            "10",
            "29"
        ],
        "temp": [
            22,
            25
        ],
        "rain": 0,
        "sun": 8.9
    },
    {
        "date": [
            "1911",
            "10",
            "30"
        ],
        "temp": [
            21.9,
            25
        ],
        "rain": 0,
        "sun": 9.7
    },
    {
        "date": [
            "1911",
            "10",
            "31"
        ],
        "temp": [
            22.7,
            26.3
        ],
        "rain": 0,
        "sun": 3
    },
    {
        "date": [
            "1911",
            "11",
            "1"
        ],
        "temp": [
            22.1,
            25.8
        ],
        "rain": 19.9,
        "sun": 0.3
    },
    {
        "date": [
            "1911",
            "11",
            "2"
        ],
        "temp": [
            21.2,
            23.8
        ],
        "rain": 0,
        "sun": 7.9
    },
    {
        "date": [
            "1911",
            "11",
            "3"
        ],
        "temp": [
            20.9,
            23.3
        ],
        "rain": 0.4,
        "sun": 1.7
    },
    {
        "date": [
            "1911",
            "11",
            "4"
        ],
        "temp": [
            21.3,
            23.1
        ],
        "rain": 0,
        "sun": 9.3
    },
    {
        "date": [
            "1911",
            "11",
            "5"
        ],
        "temp": [
            20.5,
            24.1
        ],
        "rain": 0,
        "sun": 6
    },
    {
        "date": [
            "1911",
            "11",
            "6"
        ],
        "temp": [
            19.3,
            24.2
        ],
        "rain": 0,
        "sun": 3.5
    },
    {
        "date": [
            "1911",
            "11",
            "7"
        ],
        "temp": [
            17.4,
            22.3
        ],
        "rain": 0,
        "sun": 10.3
    },
    {
        "date": [
            "1911",
            "11",
            "8"
        ],
        "temp": [
            17.1,
            22.4
        ],
        "rain": 0,
        "sun": 10.2
    },
    {
        "date": [
            "1911",
            "11",
            "9"
        ],
        "temp": [
            17.8,
            23.3
        ],
        "rain": 0,
        "sun": 9.2
    },
    {
        "date": [
            "1911",
            "11",
            "10"
        ],
        "temp": [
            18.6,
            22.9
        ],
        "rain": 0,
        "sun": 9.7
    },
    {
        "date": [
            "1911",
            "11",
            "11"
        ],
        "temp": [
            20.2,
            22.9
        ],
        "rain": 0,
        "sun": 6.4
    },
    {
        "date": [
            "1911",
            "11",
            "12"
        ],
        "temp": [
            21.3,
            24.9
        ],
        "rain": 0,
        "sun": 7
    },
    {
        "date": [
            "1911",
            "11",
            "13"
        ],
        "temp": [
            20.3,
            22.8
        ],
        "rain": 4.5,
        "sun": 0
    },
    {
        "date": [
            "1911",
            "11",
            "14"
        ],
        "temp": [
            20.2,
            23.4
        ],
        "rain": 3.7,
        "sun": 1.2
    },
    {
        "date": [
            "1911",
            "11",
            "15"
        ],
        "temp": [
            21.4,
            24.3
        ],
        "rain": 4.2,
        "sun": 3.5
    },
    {
        "date": [
            "1911",
            "11",
            "16"
        ],
        "temp": [
            22.2,
            26
        ],
        "rain": 0,
        "sun": 9
    },
    {
        "date": [
            "1911",
            "11",
            "17"
        ],
        "temp": [
            20.5,
            26.9
        ],
        "rain": 0.3,
        "sun": 4.7
    },
    {
        "date": [
            "1911",
            "11",
            "18"
        ],
        "temp": [
            19,
            24.7
        ],
        "rain": 0,
        "sun": 6.6
    },
    {
        "date": [
            "1911",
            "11",
            "19"
        ],
        "temp": [
            18.9,
            23.1
        ],
        "rain": 0,
        "sun": 7.9
    },
    {
        "date": [
            "1911",
            "11",
            "20"
        ],
        "temp": [
            18.1,
            24
        ],
        "rain": 0,
        "sun": 8.2
    },
    {
        "date": [
            "1911",
            "11",
            "21"
        ],
        "temp": [
            20.6,
            23.3
        ],
        "rain": 0,
        "sun": 8.1
    },
    {
        "date": [
            "1911",
            "11",
            "22"
        ],
        "temp": [
            19.4,
            25
        ],
        "rain": 0,
        "sun": 6.7
    },
    {
        "date": [
            "1911",
            "11",
            "23"
        ],
        "temp": [
            14.6,
            22.9
        ],
        "rain": 0,
        "sun": 10.2
    },
    {
        "date": [
            "1911",
            "11",
            "24"
        ],
        "temp": [
            13.2,
            21.2
        ],
        "rain": 0,
        "sun": 6.3
    },
    {
        "date": [
            "1911",
            "11",
            "25"
        ],
        "temp": [
            15,
            19.6
        ],
        "rain": 11.2,
        "sun": 0.2
    },
    {
        "date": [
            "1911",
            "11",
            "26"
        ],
        "temp": [
            15,
            18.6
        ],
        "rain": 6.3,
        "sun": 1
    },
    {
        "date": [
            "1911",
            "11",
            "27"
        ],
        "temp": [
            15.4,
            18.1
        ],
        "rain": 16.7,
        "sun": 0
    },
    {
        "date": [
            "1911",
            "11",
            "28"
        ],
        "temp": [
            14.7,
            17.1
        ],
        "rain": 0.7,
        "sun": 0
    },
    {
        "date": [
            "1911",
            "11",
            "29"
        ],
        "temp": [
            17,
            18.9
        ],
        "rain": 0.7,
        "sun": 0
    },
    {
        "date": [
            "1911",
            "11",
            "30"
        ],
        "temp": [
            18.3,
            20.2
        ],
        "rain": 0.6,
        "sun": 0
    },
    {
        "date": [
            "1911",
            "12",
            "1"
        ],
        "temp": [
            19.5,
            22.4
        ],
        "rain": 0,
        "sun": 8.7
    },
    {
        "date": [
            "1911",
            "12",
            "2"
        ],
        "temp": [
            19.5,
            23.6
        ],
        "rain": 0,
        "sun": 5.3
    },
    {
        "date": [
            "1911",
            "12",
            "3"
        ],
        "temp": [
            20,
            22.9
        ],
        "rain": 0,
        "sun": 0
    },
    {
        "date": [
            "1911",
            "12",
            "4"
        ],
        "temp": [
            19.7,
            22.6
        ],
        "rain": 0,
        "sun": 6
    },
    {
        "date": [
            "1911",
            "12",
            "5"
        ],
        "temp": [
            19.8,
            22.5
        ],
        "rain": 0,
        "sun": 9.4
    },
    {
        "date": [
            "1911",
            "12",
            "6"
        ],
        "temp": [
            18.6,
            22.6
        ],
        "rain": 0,
        "sun": 0.8
    },
    {
        "date": [
            "1911",
            "12",
            "7"
        ],
        "temp": [
            18.3,
            21
        ],
        "rain": 0.1,
        "sun": 7.6
    },
    {
        "date": [
            "1911",
            "12",
            "8"
        ],
        "temp": [
            18.1,
            22.9
        ],
        "rain": 0,
        "sun": 8.1
    },
    {
        "date": [
            "1911",
            "12",
            "9"
        ],
        "temp": [
            14.8,
            21.3
        ],
        "rain": 0,
        "sun": 10.1
    },
    {
        "date": [
            "1911",
            "12",
            "10"
        ],
        "temp": [
            14.3,
            18.2
        ],
        "rain": 0,
        "sun": 5
    },
    {
        "date": [
            "1911",
            "12",
            "11"
        ],
        "temp": [
            12.6,
            18.6
        ],
        "rain": 0,
        "sun": 4.9
    },
    {
        "date": [
            "1911",
            "12",
            "12"
        ],
        "temp": [
            14.4,
            18.8
        ],
        "rain": 0,
        "sun": 1.2
    },
    {
        "date": [
            "1911",
            "12",
            "13"
        ],
        "temp": [
            17.1,
            22.3
        ],
        "rain": 0,
        "sun": 0.8
    },
    {
        "date": [
            "1911",
            "12",
            "14"
        ],
        "temp": [
            13.2,
            21.6
        ],
        "rain": 0,
        "sun": 7.7
    },
    {
        "date": [
            "1911",
            "12",
            "15"
        ],
        "temp": [
            11.7,
            18.8
        ],
        "rain": 0,
        "sun": 10
    },
    {
        "date": [
            "1911",
            "12",
            "16"
        ],
        "temp": [
            12.4,
            18.9
        ],
        "rain": 0,
        "sun": 5.6
    },
    {
        "date": [
            "1911",
            "12",
            "17"
        ],
        "temp": [
            16.3,
            19.1
        ],
        "rain": 0,
        "sun": 5.8
    },
    {
        "date": [
            "1911",
            "12",
            "18"
        ],
        "temp": [
            17.6,
            20.2
        ],
        "rain": 0,
        "sun": 1.1
    },
    {
        "date": [
            "1911",
            "12",
            "19"
        ],
        "temp": [
            19.2,
            23.9
        ],
        "rain": 0,
        "sun": 1.8
    },
    {
        "date": [
            "1911",
            "12",
            "20"
        ],
        "temp": [
            16.9,
            20.4
        ],
        "rain": 0.7,
        "sun": 0.2
    },
    {
        "date": [
            "1911",
            "12",
            "21"
        ],
        "temp": [
            16.8,
            18.2
        ],
        "rain": 0.3,
        "sun": 0
    },
    {
        "date": [
            "1911",
            "12",
            "22"
        ],
        "temp": [
            15.4,
            18.1
        ],
        "rain": 0.1,
        "sun": 0
    },
    {
        "date": [
            "1911",
            "12",
            "23"
        ],
        "temp": [
            15.2,
            17.3
        ],
        "rain": 0,
        "sun": 0
    },
    {
        "date": [
            "1911",
            "12",
            "24"
        ],
        "temp": [
            16.1,
            20.7
        ],
        "rain": 0.6,
        "sun": 1.3
    },
    {
        "date": [
            "1911",
            "12",
            "25"
        ],
        "temp": [
            13.4,
            18.9
        ],
        "rain": 0,
        "sun": 2.9
    },
    {
        "date": [
            "1911",
            "12",
            "26"
        ],
        "temp": [
            12.3,
            16.7
        ],
        "rain": 0,
        "sun": 0.4
    },
    {
        "date": [
            "1911",
            "12",
            "27"
        ],
        "temp": [
            15.1,
            20.2
        ],
        "rain": 0.4,
        "sun": 4.7
    },
    {
        "date": [
            "1911",
            "12",
            "28"
        ],
        "temp": [
            14.9,
            19.8
        ],
        "rain": 0.3,
        "sun": 4
    },
    {
        "date": [
            "1911",
            "12",
            "29"
        ],
        "temp": [
            11.7,
            18.4
        ],
        "rain": 0,
        "sun": 8.4
    },
    {
        "date": [
            "1911",
            "12",
            "30"
        ],
        "temp": [
            12.3,
            19.5
        ],
        "rain": 0,
        "sun": 8.7
    },
    {
        "date": [
            "1911",
            "12",
            "31"
        ],
        "temp": [
            13.9,
            18.1
        ],
        "rain": 0,
        "sun": 3.4
    }
]